<?xml version="1.0" encoding="utf-8" ?>
<Defs>

  <!-- ================================= Industrial ==================================== -->

  <ThingDef ParentName="BaseHumanMakeableGun">
    <defName>Gun</defName>
    <label>Gun</label>
    <description>GN Placeholder.</description>
    <graphicData>
      <texPath>Things/Weapons/Gun</texPath>
      <graphicClass>Graphic_Single</graphicClass>
    </graphicData>
    <uiIconScale>1.5</uiIconScale>
    <soundInteract>Interact_Autopistol</soundInteract>
    <recipeMaker>
      <researchPrerequisite>GN_Research</researchPrerequisite>
      <skillRequirements>
        <Crafting>4</Crafting>
      </skillRequirements>
    </recipeMaker>
    <weaponTags>
      <li>SimpleGun</li>
    </weaponTags>
    <statBases>
      <WorkToMake>300</WorkToMake>
      <Mass>1.2</Mass>
      <AccuracyTouch>0.80</AccuracyTouch>
      <AccuracyShort>0.70</AccuracyShort>
      <AccuracyMedium>0.40</AccuracyMedium>
      <AccuracyLong>0.30</AccuracyLong>
      <RangedWeapon_Cooldown>1</RangedWeapon_Cooldown>
    </statBases>
    <costList>
      <Steel>20</Steel>
      <ComponentIndustrial>4</ComponentIndustrial>
      <Chemfuel>10</Chemfuel>
    </costList>
    <verbs>
      <li>
        <verbClass>Verb_Shoot</verbClass>
        <hasStandardCommand>true</hasStandardCommand>
        <defaultProjectile>Bullet_AssaultRifle</defaultProjectile>
        <warmupTime>0.3</warmupTime>
        <range>25.9</range>
        <soundCast>Shot_AssaultRifle</soundCast>
        <soundCastTail>GunTail_Light</soundCastTail>
        <muzzleFlashScale>9</muzzleFlashScale>
        <burstShotCount>3</burstShotCount>
        <ticksBetweenBurstShots>7</ticksBetweenBurstShots>
      </li>
    </verbs>
    <tools>
      <li>
        <label>grip</label>
        <capacities>
          <li>Blunt</li>
        </capacities>
        <power>9</power>
        <cooldownTime>2</cooldownTime>
      </li>
      <li>
        <label>barrel</label>
        <capacities>
          <li>Blunt</li>
          <li>Poke</li>
        </capacities>
        <power>9</power>
        <cooldownTime>2</cooldownTime>
      </li>
    </tools>
  </ThingDef>
</Defs>